odoo/addons/sale_order_import_ubl_line_customer_ref/README.rst
odoo/addons/sale_order_import_ubl_line_customer_ref/__init__.py
odoo/addons/sale_order_import_ubl_line_customer_ref/__manifest__.py
odoo/addons/sale_order_import_ubl_line_customer_ref/i18n/sale_order_import_ubl_line_customer_ref.pot
odoo/addons/sale_order_import_ubl_line_customer_ref/readme/CONTRIBUTORS.rst
odoo/addons/sale_order_import_ubl_line_customer_ref/readme/DESCRIPTION.rst
odoo/addons/sale_order_import_ubl_line_customer_ref/static/description/icon.png
odoo/addons/sale_order_import_ubl_line_customer_ref/static/description/index.html
odoo/addons/sale_order_import_ubl_line_customer_ref/tests/__init__.py
odoo/addons/sale_order_import_ubl_line_customer_ref/tests/test_order_line_customer_ref.py
odoo/addons/sale_order_import_ubl_line_customer_ref/wizard/__init__.py
odoo/addons/sale_order_import_ubl_line_customer_ref/wizard/sale_order_import.py
odoo14_addon_sale_order_import_ubl_line_customer_ref-14.0.1.0.2.dist-info/METADATA
odoo14_addon_sale_order_import_ubl_line_customer_ref-14.0.1.0.2.dist-info/WHEEL
odoo14_addon_sale_order_import_ubl_line_customer_ref-14.0.1.0.2.dist-info/top_level.txt
odoo14_addon_sale_order_import_ubl_line_customer_ref-14.0.1.0.2.dist-info/RECORD
