Metadata-Version: 2.1
Name: odoo14-addon-sale-order-import-ubl-line-customer-ref
Version: 14.0.1.0.2
Summary: Extract specific customer reference for each order line
Home-page: https://github.com/OCA/edi
Author: Camptocamp, Odoo Community Association (OCA)
Author-email: support@odoo-community.org
License: AGPL-3
Platform: UNKNOWN
Classifier: Programming Language :: Python
Classifier: Framework :: Odoo
Classifier: Framework :: Odoo :: 14.0
Classifier: License :: OSI Approved :: GNU Affero General Public License v3
Requires-Python: >=3.6
Requires-Dist: odoo14-addon-sale-order-import-ubl
Requires-Dist: odoo14-addon-sale-stock-line-customer-ref
Requires-Dist: odoo (<14.1dev,>=14.0a)
